ciocore/VERSION
ciocore/__init__.py
ciocore/api_client.py
ciocore/cli.py
ciocore/client_db.py
ciocore/common.py
ciocore/conductor_submit.py
ciocore/config.py
ciocore/data.py
ciocore/exceptions.py
ciocore/file_utils.py
ciocore/hardware_set.py
ciocore/loggeria.py
ciocore/package_environment.py
ciocore/package_query.py
ciocore/package_tree.py
ciocore/post_install.py
ciocore/retry.py
ciocore/validator.py
ciocore/worker.py
ciocore/auth/__init__.py
ciocore/auth/server.py
ciocore/docsite/404.html
ciocore/docsite/index.html
ciocore/docsite/logo.png
ciocore/docsite/objects.inv
ciocore/docsite/sitemap.xml
ciocore/docsite/sitemap.xml.gz
ciocore/docsite/apidoc/api_client/index.html
ciocore/docsite/apidoc/apidoc/index.html
ciocore/docsite/apidoc/config/index.html
ciocore/docsite/apidoc/data/index.html
ciocore/docsite/apidoc/hardware_set/index.html
ciocore/docsite/apidoc/package_environment/index.html
ciocore/docsite/apidoc/package_tree/index.html
ciocore/docsite/assets/_mkdocstrings.css
ciocore/docsite/assets/images/favicon.png
ciocore/docsite/assets/javascripts/bundle.471ce7a9.min.js
ciocore/docsite/assets/javascripts/bundle.471ce7a9.min.js.map
ciocore/docsite/assets/javascripts/lunr/tinyseg.js
ciocore/docsite/assets/javascripts/lunr/wordcut.js
ciocore/docsite/assets/javascripts/lunr/min/lunr.ar.min.js
ciocore/docsite/assets/javascripts/lunr/min/lunr.da.min.js
ciocore/docsite/assets/javascripts/lunr/min/lunr.de.min.js
ciocore/docsite/assets/javascripts/lunr/min/lunr.du.min.js
ciocore/docsite/assets/javascripts/lunr/min/lunr.el.min.js
ciocore/docsite/assets/javascripts/lunr/min/lunr.es.min.js
ciocore/docsite/assets/javascripts/lunr/min/lunr.fi.min.js
ciocore/docsite/assets/javascripts/lunr/min/lunr.fr.min.js
ciocore/docsite/assets/javascripts/lunr/min/lunr.he.min.js
ciocore/docsite/assets/javascripts/lunr/min/lunr.hi.min.js
ciocore/docsite/assets/javascripts/lunr/min/lunr.hu.min.js
ciocore/docsite/assets/javascripts/lunr/min/lunr.hy.min.js
ciocore-9.1.1.dist-info/METADATA
ciocore-9.1.1.dist-info/WHEEL
ciocore-9.1.1.dist-info/entry_points.txt
ciocore-9.1.1.dist-info/top_level.txt
ciocore-9.1.1.dist-info/RECORD
