Metadata-Version: 2.4
Name: ciocore
Version: 9.1.1
Summary: Core functionality for Conductor's client tools
Home-page: https://github.com/ConductorTechnologies/ciocore
Author: conductor
Author-email: info@conductortech.com
Classifier: Operating System :: OS Independent
Classifier: Programming Language :: Python
Classifier: Topic :: Multimedia :: Graphics :: 3D Rendering
Requires-Dist: requests>=2.31.0
Requires-Dist: pyjwt==2.9.0
Requires-Dist: cioseq<1.0.0,>=0.4.1
Requires-Dist: Click<9.0.0,>=8.1.3
Requires-Dist: markdown<4.0.0,>=3.5.2
Requires-Dist: colorlog<7.0.0,>=6.8.2
Dynamic: author
Dynamic: author-email
Dynamic: classifier
Dynamic: description
Dynamic: description-content-type
Dynamic: home-page
Dynamic: requires-dist
Dynamic: summary
